tidegear/__init__.py
tidegear/_constants.py
tidegear/aiohttp.py
tidegear/chat_formatting.py
tidegear/cog.py
tidegear/converters.py
tidegear/exceptions.py
tidegear/metadata.py
tidegear/py.typed
tidegear/tidegear.py
tidegear/types.py
tidegear/utils.py
tidegear/version.py
tidegear/assets/arrow.png
tidegear/config/__init__.py
tidegear/config/exceptions.py
tidegear/config/options.py
tidegear/config/schema.py
tidegear/config/types.py
tidegear/locales/messages.pot
tidegear/pydantic/__init__.py
tidegear/pydantic/basemodel.py
tidegear/pydantic/cogmodel.py
tidegear/pydantic/httpurl.py
tidegear/sentinel/__init__.py
tidegear/sentinel/cog.py
tidegear/sentinel/config.py
tidegear/sentinel/exceptions.py
tidegear/sentinel/moderation_type.py
tidegear/sentinel/db/__init__.py
tidegear/sentinel/db/piccolo_app.py
tidegear/sentinel/db/piccolo_conf.py
tidegear/sentinel/db/tables.py
tidegear/sentinel/db/migrations/__init__.py
tidegear/sentinel/db/migrations/tidegearsentinel_2025_09_24t04_42_24_416049.py
tidegear/sentinel/db/migrations/tidegearsentinel_2025_09_26t09_29_17_713551.py
tidegear/sentinel/db/migrations/tidegearsentinel_2025_12_14t05_01_06_355900.py
tidegear/sentinel/importers/__init__.py
tidegear/sentinel/importers/aurora.py
tidegear/sentinel/locales/messages.pot
red_tidegear-1.27.3.dist-info/METADATA
red_tidegear-1.27.3.dist-info/WHEEL
red_tidegear-1.27.3.dist-info/RECORD
