Metadata-Version: 2.4
Name: red-tidegear
Version: 1.27.3
Summary: A small collection of utilities for cog creation with Red-DiscordBot.
Project-URL: Homepage, https://c.csw.im/cswimr/tidegear
Project-URL: Documentation, https://tidegear.csw.im
Project-URL: Issues, https://c.csw.im/cswimr/tidegear/issues
Project-URL: Source Archive, https://c.csw.im/cswimr/tidegear/archive/0db22c2a8d7d5de38190a97ca864f07bb7275b14.tar.gz
Author-email: cswimr <cswimr@csw.im>
License-Expression: MPL-2.0
Classifier: Programming Language :: Python
Classifier: Programming Language :: Python :: 3.11
Requires-Python: <3.12,>=3.11
Requires-Dist: emoji~=2.15.0
Requires-Dist: humanize~=4.14
Requires-Dist: pip
Requires-Dist: pydantic-extra-types[all]~=2.11.0
Requires-Dist: pydantic~=2.11.0
Requires-Dist: pypiwrap~=2.0
Requires-Dist: red-discordbot~=3.5.6
Provides-Extra: sentinel
Requires-Dist: phx-class-registry~=5.1; extra == 'sentinel'
Requires-Dist: piccolo[sqlite]~=1.30.0; extra == 'sentinel'
Requires-Dist: redbot-orm~=1.0.2; extra == 'sentinel'
